{
  "version": "7",
  "dialect": "postgresql",
  "entries": [
    {
      "idx": 0,
      "version": "7",
      "when": 1783732082682,
      "tag": "0000_stiff_stick",
      "breakpoints": true
    },
    {
      "idx": 1,
      "version": "7",
      "when": 1783734673280,
      "tag": "0001_narrow_vargas",
      "breakpoints": true
    },
    {
      "idx": 2,
      "version": "7",
      "when": 1783735302905,
      "tag": "0002_hard_major_mapleleaf",
      "breakpoints": true
    },
    {
      "idx": 3,
      "version": "7",
      "when": 1783735575492,
      "tag": "0003_tranquil_storm",
      "breakpoints": true
    },
    {
      "idx": 4,
      "version": "7",
      "when": 1783736342382,
      "tag": "0004_puzzling_grandmaster",
      "breakpoints": true
    },
    {
      "idx": 5,
      "version": "7",
      "when": 1783737186928,
      "tag": "0005_left_strong_guy",
      "breakpoints": true
    },
    {
      "idx": 6,
      "version": "7",
      "when": 1783738289748,
      "tag": "0006_round_lady_bullseye",
      "breakpoints": true
    },
    {
      "idx": 7,
      "version": "7",
      "when": 1783738695639,
      "tag": "0007_lively_miracleman",
      "breakpoints": true
    },
    {
      "idx": 8,
      "version": "7",
      "when": 1783739009013,
      "tag": "0008_faulty_lilandra",
      "breakpoints": true
    },
    {
      "idx": 9,
      "version": "7",
      "when": 1783739422578,
      "tag": "0009_glossy_karnak",
      "breakpoints": true
    },
    {
      "idx": 10,
      "version": "7",
      "when": 1783740306746,
      "tag": "0010_calm_freak",
      "breakpoints": true
    },
    {
      "idx": 11,
      "version": "7",
      "when": 1783741580207,
      "tag": "0011_third_franklin_richards",
      "breakpoints": true
    },
    {
      "idx": 12,
      "version": "7",
      "when": 1783784765025,
      "tag": "0012_tiny_metal_master",
      "breakpoints": true
    },
    {
      "idx": 13,
      "version": "7",
      "when": 1783785962989,
      "tag": "0013_perpetual_rictor",
      "breakpoints": true
    },
    {
      "idx": 14,
      "version": "7",
      "when": 1783787594327,
      "tag": "0014_loose_mockingbird",
      "breakpoints": true
    },
    {
      "idx": 15,
      "version": "7",
      "when": 1783802022947,
      "tag": "0015_square_alex_power",
      "breakpoints": true
    },
    {
      "idx": 16,
      "version": "7",
      "when": 1783805240569,
      "tag": "0016_skinny_liz_osborn",
      "breakpoints": true
    },
    {
      "idx": 17,
      "version": "7",
      "when": 1784408939556,
      "tag": "0017_greedy_marvex",
      "breakpoints": true
    },
    {
      "idx": 18,
      "version": "7",
      "when": 1784440554393,
      "tag": "0018_short_revanche",
      "breakpoints": true
    },
    {
      "idx": 19,
      "version": "7",
      "when": 1784497243924,
      "tag": "0019_secret_ben_parker",
      "breakpoints": true
    }
  ]
}